{
  "gitSyncId": "670a2c74cb4eb2140bfd1e60_e7cb96f7-fac0-4203-a8cc-969e405e765f",
  "id": "konfigurator-screeny_Select_sterowania2",
  "pluginId": "mysql-plugin",
  "pluginType": "DB",
  "unpublishedAction": {
    "actionConfiguration": {
      "body": "SELECT * FROM  sterowania WHERE fk_oferty_inventory_id_ster = {{appsmith.URL.queryParams.id_oferta}}\n \n",
      "encodeParamsToggle": true,
      "paginationType": "NONE",
      "pluginSpecifiedTemplates": [
        {
          "value": false
        }
      ],
      "timeoutInMillisecond": 10000
    },
    "confirmBeforeExecute": false,
    "datasource": {
      "id": "app-sigma",
      "isAutoGenerated": false,
      "name": "app-sigma",
      "pluginId": "mysql-plugin"
    },
    "dynamicBindingPathList": [
      {
        "key": "body"
      }
    ],
    "executeOnLoad": true,
    "name": "Select_sterowania2",
    "pageId": "konfigurator-screeny",
    "userSetOnLoad": true
  }
}