{
  "animateLoading": true,
  "borderOpacity": 100,
  "borderRadius": "{{appsmith.theme.borderRadius.appBorderRadius}}",
  "borderWidth": "0",
  "bottomRow": 76,
  "boxShadow": "{{appsmith.theme.boxShadow.appBoxShadow}}",
  "dynamicBindingPathList": [
    {
      "key": "borderRadius"
    },
    {
      "key": "boxShadow"
    }
  ],
  "dynamicTriggerPathList": [],
  "flexVerticalAlignment": "start",
  "isLoading": false,
  "isVisible": true,
  "key": "l56xt5i7rt",
  "leftColumn": 0,
  "mobileBottomRow": 42,
  "mobileLeftColumn": 5,
  "mobileRightColumn": 29,
  "mobileTopRow": 10,
  "needsErrorInfo": false,
  "parentColumnSpace": 6.9375,
  "parentId": "2xlcdboau8",
  "parentRowSpace": 10,
  "renderMode": "CANVAS",
  "responsiveBehavior": "fill",
  "rightColumn": 64,
  "source": "http://serwer.hosting-sanok.pl/screeny.html",
  "topRow": 4,
  "type": "IFRAME_WIDGET",
  "version": 1,
  "widgetId": "yinxy13msf",
  "widgetName": "Iframe2"
}