{
  "accentColor": "{{appsmith.theme.colors.primaryColor}}",
  "animateLoading": true,
  "autoFocus": false,
  "borderRadius": "{{appsmith.theme.borderRadius.appBorderRadius}}",
  "bottomRow": 32,
  "boxShadow": "none",
  "defaultText": "{{iloscsterowania.data[0][\"COUNT(model)\"]}}",
  "dynamicBindingPathList": [
    {
      "key": "accentColor"
    },
    {
      "key": "borderRadius"
    },
    {
      "key": "defaultText"
    }
  ],
  "dynamicHeight": "FIXED",
  "dynamicTriggerPathList": [],
  "iconAlign": "left",
  "inputType": "TEXT",
  "isDisabled": false,
  "isLoading": false,
  "isRequired": false,
  "isVisible": true,
  "key": "23cppxcmj2",
  "label": "Label",
  "labelAlignment": "left",
  "labelPosition": "Top",
  "labelStyle": "",
  "labelTextSize": "0.875rem",
  "labelWidth": 5,
  "leftColumn": 0,
  "maxDynamicHeight": 9000,
  "minDynamicHeight": 4,
  "minWidth": 450,
  "mobileBottomRow": 27,
  "mobileLeftColumn": 0,
  "mobileRightColumn": 12,
  "mobileTopRow": 20,
  "needsErrorInfo": false,
  "parentColumnSpace": 19.90625,
  "parentId": "esfh9fxray",
  "parentRowSpace": 10,
  "renderMode": "CANVAS",
  "resetOnSubmit": true,
  "responsiveBehavior": "fill",
  "rightColumn": 12,
  "showStepArrows": false,
  "topRow": 25,
  "type": "INPUT_WIDGET_V2",
  "version": 2,
  "widgetId": "hvfqunlzaa",
  "widgetName": "Input26"
}