{
  "gitSyncId": "66db510001b5f41415619b59_7a7d9f66-6b35-433d-b9ad-0a7f86cd1dd2",
  "id": "Screeny_system_POBIERZLINIE",
  "pluginId": "mysql-plugin",
  "pluginType": "DB",
  "unpublishedAction": {
    "actionConfiguration": {
      "body": "SELECT DISTINCT linia FROM screeny_system;",
      "encodeParamsToggle": true,
      "paginationType": "NONE",
      "pluginSpecifiedTemplates": [
        {
          "value": true
        }
      ],
      "timeoutInMillisecond": 10000
    },
    "confirmBeforeExecute": false,
    "datasource": {
      "id": "app-sigma",
      "isAutoGenerated": false,
      "name": "app-sigma",
      "pluginId": "mysql-plugin"
    },
    "dynamicBindingPathList": [],
    "executeOnLoad": true,
    "name": "POBIERZLINIE",
    "pageId": "Screeny_system",
    "userSetOnLoad": false
  }
}