{
  "gitSyncId": "66db510001b5f41415619b59_b329a243-a65d-45f6-a2f8-c3a60b4b043a",
  "id": "Screeny_tabelaindeksy_SelectQuery",
  "pluginId": "mysql-plugin",
  "pluginType": "DB",
  "unpublishedAction": {
    "actionConfiguration": {
      "body": "SELECT * FROM screeny_tabelaindeksy\nORDER BY {{data_table.sortOrder.column || 'id'}} {{data_table.sortOrder.order || \"ASC\"}}\nLIMIT {{data_table.pageSize}}\nOFFSET {{(data_table.pageNo - 1) * data_table.pageSize}};",
      "encodeParamsToggle": true,
      "paginationType": "NONE",
      "pluginSpecifiedTemplates": [
        {
          "value": false
        }
      ],
      "timeoutInMillisecond": 10000
    },
    "confirmBeforeExecute": false,
    "datasource": {
      "id": "app-sigma",
      "isAutoGenerated": false,
      "name": "app-sigma",
      "pluginId": "mysql-plugin"
    },
    "dynamicBindingPathList": [
      {
        "key": "body"
      }
    ],
    "executeOnLoad": true,
    "name": "SelectQuery",
    "pageId": "Screeny_tabelaindeksy",
    "userSetOnLoad": true
  }
}