{
  "gitSyncId": "670a2c74cb4eb2140bfd1e60_53b073f1-bd8d-4ad9-a148-706fec5b146f",
  "id": "konfigurator-screeny_przeliczoferte",
  "pluginId": "mysql-plugin",
  "pluginType": "DB",
  "unpublishedAction": {
    "actionConfiguration": {
      "body": "UPDATE screeny_inventory SET\nkwotarabatsystem = CASE \n   {{tabela_screeny_inventory_id.updatedRows.map((user) => `WHEN id = ${user.id} THEN '${user.updatedFields.kwotarabatsystem}'`).join('\\n')}}\nEND\n\nWHERE id IN ({{tabela_screeny_inventory_id.updatedRows.map((user) => user.allFields.id).join(',')}});",
      "encodeParamsToggle": true,
      "paginationType": "NONE",
      "pluginSpecifiedTemplates": [
        {
          "value": false
        }
      ],
      "timeoutInMillisecond": 10000
    },
    "confirmBeforeExecute": false,
    "datasource": {
      "id": "app-sigma",
      "isAutoGenerated": false,
      "name": "app-sigma",
      "pluginId": "mysql-plugin"
    },
    "dynamicBindingPathList": [
      {
        "key": "body"
      }
    ],
    "executeOnLoad": false,
    "name": "przeliczoferte",
    "pageId": "konfigurator-screeny",
    "userSetOnLoad": false
  }
}