{
  "accentColor": "{{appsmith.theme.colors.primaryColor}}",
  "animateLoading": true,
  "autoFocus": false,
  "borderRadius": "{{appsmith.theme.borderRadius.appBorderRadius}}",
  "bottomRow": 7,
  "boxShadow": "none",
  "defaultText": "{{napedwybrany.data[0].model}}",
  "dynamicBindingPathList": [
    {
      "key": "accentColor"
    },
    {
      "key": "borderRadius"
    },
    {
      "key": "isVisible"
    },
    {
      "key": "defaultText"
    }
  ],
  "dynamicHeight": "FIXED",
  "dynamicPropertyPathList": [
    {
      "key": "isVisible"
    }
  ],
  "dynamicTriggerPathList": [
    {
      "key": "onTextChanged"
    }
  ],
  "iconAlign": "left",
  "inputType": "TEXT",
  "isDisabled": true,
  "isLoading": false,
  "isRequired": true,
  "isVisible": "{{sku_input.text.length > 0 }}",
  "key": "191agobene",
  "label": "Napęd",
  "labelAlignment": "left",
  "labelPosition": "Top",
  "labelStyle": "",
  "labelTextSize": "0.875rem",
  "labelWidth": 5,
  "leftColumn": 46,
  "maxDynamicHeight": 9000,
  "minDynamicHeight": 4,
  "minWidth": 450,
  "mobileBottomRow": 14,
  "mobileLeftColumn": 41,
  "mobileRightColumn": 61,
  "mobileTopRow": 7,
  "needsErrorInfo": false,
  "onTextChanged": "",
  "originalBottomRow": 40,
  "originalTopRow": 33,
  "parentColumnSpace": 18.6884765625,
  "parentId": "esfh9fxray",
  "parentRowSpace": 10,
  "renderMode": "CANVAS",
  "resetOnSubmit": true,
  "responsiveBehavior": "fill",
  "rightColumn": 53,
  "showStepArrows": false,
  "topRow": 0,
  "type": "INPUT_WIDGET_V2",
  "version": 2,
  "widgetId": "luy2zdyfve",
  "widgetName": "Input8"
}