{
  "borderColor": "#d4d4d8",
  "borderRadius": "0px",
  "borderWidth": "",
  "bottomRow": 13,
  "boxShadow": "none",
  "dynamicBindingPathList": [
    {
      "key": "text"
    }
  ],
  "dynamicHeight": "FIXED",
  "dynamicPropertyPathList": [
    {
      "key": "fontSize"
    }
  ],
  "dynamicTriggerPathList": [],
  "fontFamily": "System Default",
  "fontSize": "1rem",
  "fontStyle": "",
  "isLoading": false,
  "isVisible": "true",
  "labelTextSize": "0.875rem",
  "leftColumn": 0,
  "maxDynamicHeight": 9000,
  "minDynamicHeight": 4,
  "overflow": "NONE",
  "parentColumnSpace": 11.78515625,
  "parentId": "59rw5mx0bq",
  "parentRowSpace": 10,
  "rightColumn": 15,
  "shouldScrollContents": true,
  "text": "Klient: {{appsmith.URL.queryParams.klient}}\nNumer oferty: {{appsmith.URL.queryParams.numer}}\nz dnia: {{appsmith.URL.queryParams.data}}",
  "textAlign": "LEFT",
  "textColor": "#231F20",
  "topRow": 6,
  "type": "TEXT_WIDGET",
  "version": 1,
  "widgetId": "urzv99hdc8",
  "widgetName": "Text16"
}