{
  "gitSyncId": "66db510001b5f41415619b59_297ba94f-a46f-45f3-9538-a65b1570a413",
  "id": "Oferty_zapytaj_klient",
  "pluginId": "mysql-plugin",
  "pluginType": "DB",
  "unpublishedAction": {
    "actionConfiguration": {
      "body": "SELECT accountname FROM klienci where accountid = {{appsmith.URL.queryParams.id_klienta}};",
      "encodeParamsToggle": true,
      "paginationType": "NONE",
      "pluginSpecifiedTemplates": [
        {
          "value": false
        }
      ],
      "timeoutInMillisecond": 10000
    },
    "confirmBeforeExecute": false,
    "datasource": {
      "id": "app-sigma",
      "isAutoGenerated": false,
      "name": "app-sigma",
      "pluginId": "mysql-plugin"
    },
    "dynamicBindingPathList": [
      {
        "key": "body"
      }
    ],
    "executeOnLoad": false,
    "name": "zapytaj_klient",
    "pageId": "Oferty",
    "userSetOnLoad": true
  }
}