{
  "animateLoading": true,
  "backgroundColor": "#FFFFFF",
  "borderColor": "#E0DEDE",
  "borderRadius": "{{appsmith.theme.borderRadius.appBorderRadius}}",
  "borderWidth": "1",
  "bottomRow": 20,
  "boxShadow": "{{appsmith.theme.boxShadow.appBoxShadow}}",
  "children": [
    {
      "borderRadius": "{{appsmith.theme.borderRadius.appBorderRadius}}",
      "bottomRow": 140,
      "boxShadow": "{{appsmith.theme.boxShadow.appBoxShadow}}",
      "canExtend": false,
      "containerStyle": "none",
      "detachFromLayout": true,
      "dynamicBindingPathList": [
        {
          "key": "borderRadius"
        },
        {
          "key": "boxShadow"
        }
      ],
      "dynamicHeight": "AUTO_HEIGHT",
      "flexLayers": [],
      "isLoading": false,
      "isVisible": true,
      "key": "bzzoyt17gd",
      "leftColumn": 0,
      "maxDynamicHeight": 9000,
      "minDynamicHeight": 4,
      "minHeight": 400,
      "minWidth": 450,
      "mobileBottomRow": 400,
      "mobileLeftColumn": 0,
      "mobileRightColumn": 279.75,
      "mobileTopRow": 0,
      "needsErrorInfo": false,
      "parentColumnSpace": 1,
      "parentId": "x760dzx7cg",
      "parentRowSpace": 1,
      "renderMode": "CANVAS",
      "responsiveBehavior": "fill",
      "rightColumn": 279.75,
      "topRow": 0,
      "type": "CANVAS_WIDGET",
      "version": 1,
      "widgetId": "sb8brmf4m8",
      "widgetName": "Canvas15"
    }
  ],
  "dynamicBindingPathList": [
    {
      "key": "borderRadius"
    },
    {
      "key": "boxShadow"
    }
  ],
  "dynamicHeight": "AUTO_HEIGHT",
  "flexVerticalAlignment": "stretch",
  "isCanvas": true,
  "isLoading": false,
  "isVisible": true,
  "key": "q5n39p59kp",
  "leftColumn": 0,
  "maxDynamicHeight": 9000,
  "minDynamicHeight": 10,
  "minWidth": 450,
  "mobileBottomRow": 66,
  "mobileLeftColumn": 3,
  "mobileRightColumn": 27,
  "mobileTopRow": 26,
  "needsErrorInfo": false,
  "originalBottomRow": 20,
  "originalTopRow": 6,
  "parentColumnSpace": 11.65625,
  "parentId": "gc1m2vg4nz",
  "parentRowSpace": 10,
  "positioning": "fixed",
  "renderMode": "CANVAS",
  "responsiveBehavior": "fill",
  "rightColumn": 63,
  "shouldScrollContents": true,
  "topRow": 6,
  "type": "FORM_WIDGET",
  "widgetId": "x760dzx7cg",
  "widgetName": "Form2"
}