{
  "gitSyncId": "670a2c74cb4eb2140bfd1e60_d7430e0e-f52b-4287-9a20-afc1ab5158b5",
  "id": "Screeny_danesku2",
  "pluginId": "mysql-plugin",
  "pluginType": "DB",
  "unpublishedAction": {
    "actionConfiguration": {
      "body": "SELECT * FROM screeny_cennik where indeks = {{tymczasowy.text}};",
      "encodeParamsToggle": true,
      "paginationType": "NONE",
      "pluginSpecifiedTemplates": [
        {
          "value": true
        }
      ],
      "timeoutInMillisecond": 10000
    },
    "confirmBeforeExecute": false,
    "datasource": {
      "id": "app-sigma",
      "isAutoGenerated": false,
      "name": "app-sigma",
      "pluginId": "mysql-plugin"
    },
    "dynamicBindingPathList": [
      {
        "key": "body"
      }
    ],
    "executeOnLoad": false,
    "name": "danesku2",
    "pageId": "Screeny",
    "userSetOnLoad": false
  }
}