{
  "gitSyncId": "66db510001b5f41415619b59_7bb835c2-9f28-4e4e-828b-a095f213b5e1",
  "id": "Screeny_kolor_DeleteQuery",
  "pluginId": "mysql-plugin",
  "pluginType": "DB",
  "unpublishedAction": {
    "actionConfiguration": {
      "body": "DELETE FROM screeny_kolor\n  WHERE id = {{data_table.triggeredRow.id}};",
      "encodeParamsToggle": true,
      "paginationType": "NONE",
      "pluginSpecifiedTemplates": [
        {
          "value": true
        }
      ],
      "timeoutInMillisecond": 10000
    },
    "confirmBeforeExecute": false,
    "datasource": {
      "id": "app-sigma",
      "isAutoGenerated": false,
      "name": "app-sigma",
      "pluginId": "mysql-plugin"
    },
    "executeOnLoad": false,
    "name": "DeleteQuery",
    "pageId": "Screeny_kolor",
    "userSetOnLoad": false
  }
}