{
  "gitSyncId": "670a2c74cb4eb2140bfd1e60_57d8ad39-0dcc-4930-abcf-f2cbee32cb80",
  "id": "Kalkulacja_ustawrabat",
  "pluginId": "mysql-plugin",
  "pluginType": "DB",
  "unpublishedAction": {
    "actionConfiguration": {
      "body": "UPDATE inventory_screeny SET\n    rabatsystem = '{{rabatsystem.text}}',\n\t  kwotarabatsystem = systemzdoplata*(rabatsystem/100),\n\t\tsystemporabacie = systemzdoplata-kwotarabatsystem,\n\t\tcenanetto = priceall+systemporabacie,\t\n\t\trazemnetto = cenanetto * ilosc\t\t\n\t\tWHERE fk_oferty_inventory_id = {{appsmith.URL.queryParams.id_oferta}};",
      "encodeParamsToggle": true,
      "paginationType": "NONE",
      "pluginSpecifiedTemplates": [
        {
          "value": true
        }
      ],
      "timeoutInMillisecond": 10000
    },
    "confirmBeforeExecute": false,
    "datasource": {
      "id": "app-sigma",
      "isAutoGenerated": false,
      "name": "app-sigma",
      "pluginId": "mysql-plugin"
    },
    "dynamicBindingPathList": [
      {
        "key": "body"
      }
    ],
    "executeOnLoad": false,
    "name": "ustawrabat",
    "pageId": "Kalkulacja",
    "userSetOnLoad": false
  }
}