{
  "accentColor": "{{appsmith.theme.colors.primaryColor}}",
  "animateLoading": true,
  "autoFocus": false,
  "borderRadius": "{{appsmith.theme.borderRadius.appBorderRadius}}",
  "bottomRow": 44,
  "boxShadow": "none",
  "defaultText": "{{Input1.text}} {{Input2.text}}",
  "dynamicBindingPathList": [
    {
      "key": "accentColor"
    },
    {
      "key": "borderRadius"
    },
    {
      "key": "defaultText"
    }
  ],
  "dynamicHeight": "FIXED",
  "dynamicTriggerPathList": [],
  "iconAlign": "left",
  "inputType": "TEXT",
  "isDisabled": false,
  "isLoading": false,
  "isRequired": false,
  "isVisible": false,
  "key": "x35xvlsqbo",
  "label": "Label",
  "labelAlignment": "left",
  "labelPosition": "Top",
  "labelStyle": "",
  "labelTextSize": "0.875rem",
  "labelWidth": 5,
  "leftColumn": 49,
  "maxDynamicHeight": 9000,
  "minDynamicHeight": 4,
  "minWidth": 450,
  "mobileBottomRow": 44,
  "mobileLeftColumn": 44,
  "mobileRightColumn": 64,
  "mobileTopRow": 37,
  "needsErrorInfo": false,
  "originalBottomRow": 44,
  "originalTopRow": 37,
  "parentColumnSpace": 20.25,
  "parentId": "3nptwm86f7",
  "parentRowSpace": 10,
  "renderMode": "CANVAS",
  "resetOnSubmit": true,
  "responsiveBehavior": "fill",
  "rightColumn": 64,
  "showStepArrows": false,
  "topRow": 37,
  "type": "INPUT_WIDGET_V2",
  "version": 2,
  "widgetId": "05i8qjzqnx",
  "widgetName": "Input17"
}