{
  "accentColor": "{{appsmith.theme.colors.primaryColor}}",
  "animateLoading": false,
  "borderColor": "rgba(46, 61, 73, 0.33)",
  "borderRadius": "0px",
  "borderWidth": "",
  "bottomRow": 89,
  "boxShadow": "none",
  "childStylesheet": {
    "button": {
      "borderRadius": "{{appsmith.theme.borderRadius.appBorderRadius}}",
      "boxShadow": "none",
      "buttonColor": "{{appsmith.theme.colors.primaryColor}}"
    },
    "iconButton": {
      "borderRadius": "{{appsmith.theme.borderRadius.appBorderRadius}}",
      "boxShadow": "none",
      "menuColor": "{{appsmith.theme.colors.primaryColor}}"
    },
    "menuButton": {
      "borderRadius": "{{appsmith.theme.borderRadius.appBorderRadius}}",
      "boxShadow": "none",
      "menuColor": "{{appsmith.theme.colors.primaryColor}}"
    }
  },
  "columnOrder": [
    "customColumn2",
    "customColumn1",
    "temat",
    "klient",
    "numeroferty",
    "dataoferty",
    "sumanetto",
    "sumabrutto",
    "customColumn4",
    "kategoria",
    "id_oferta",
    "id_klient",
    "fk_klienci_oferty_id",
    "kurseuro",
    "waluta",
    "vat",
    "rabat",
    "komentarz",
    "wymaganyzadatekprocent",
    "wymaganyzadatek",
    "datawaznosci",
    "warunkiplatnosci",
    "sugerowanyzadatek",
    "sumarabatu",
    "tabelanbpkurs",
    "kurswgtabeli",
    "narzut"
  ],
  "columnSizeMap": {
    "status": 75,
    "step": 62,
    "task": 245
  },
  "columnUpdatedAt": 1730663581166,
  "columnWidthMap": {
    "customColumn1": 102,
    "customColumn2": 80,
    "customColumn3": 111,
    "customColumn4": 174.99999999999997,
    "kategoria": 329,
    "temat": 111
  },
  "compactMode": "DEFAULT",
  "defaultPageSize": 0,
  "defaultSelectedRowIndex": "0",
  "delimiter": ",",
  "derivedColumns": {
    "customColumn1": {
      "borderRadius": "0px",
      "boxShadow": "none",
      "buttonColor": "#DD4B34",
      "buttonLabel": "{{data_table.processedTableData.map((currentRow, currentIndex) => ( 'Delete'))}}",
      "buttonLabelColor": "#FFFFFF",
      "buttonStyle": "rgb(3, 179, 101)",
      "columnType": "button",
      "computedValue": "",
      "enableFilter": true,
      "enableSort": true,
      "id": "customColumn1",
      "index": 5,
      "isCellVisible": true,
      "isDerived": true,
      "isDisabled": false,
      "isVisible": true,
      "label": "Delete",
      "labelColor": "#FFFFFF",
      "menuColor": "#03B365",
      "onClick": "{{showModal('Delete_Modal')}}",
      "width": 150
    }
  },
  "displayName": "Table",
  "dynamicBindingPathList": [
    {
      "key": "tableData"
    },
    {
      "key": "primaryColumns.fk_klienci_oferty_id.computedValue"
    },
    {
      "key": "primaryColumns.customColumn1.computedValue"
    },
    {
      "key": "primaryColumns.dataoferty.computedValue"
    },
    {
      "key": "primaryColumns.customColumn4.boxShadow"
    },
    {
      "key": "primaryColumns.numeroferty.computedValue"
    },
    {
      "key": "primaryColumns.id_klient.computedValue"
    },
    {
      "key": "primaryColumns.id_oferta.computedValue"
    },
    {
      "key": "primaryColumns.klient.computedValue"
    },
    {
      "key": "primaryColumns.temat.computedValue"
    },
    {
      "key": "accentColor"
    },
    {
      "key": "primaryColumns.kategoria.computedValue"
    },
    {
      "key": "primaryColumns.kurseuro.computedValue"
    },
    {
      "key": "primaryColumns.waluta.computedValue"
    },
    {
      "key": "primaryColumns.vat.computedValue"
    },
    {
      "key": "primaryColumns.rabat.computedValue"
    },
    {
      "key": "primaryColumns.komentarz.computedValue"
    },
    {
      "key": "primaryColumns.wymaganyzadatekprocent.computedValue"
    },
    {
      "key": "primaryColumns.wymaganyzadatek.computedValue"
    },
    {
      "key": "primaryColumns.datawaznosci.computedValue"
    },
    {
      "key": "primaryColumns.warunkiplatnosci.computedValue"
    },
    {
      "key": "primaryColumns.sumanetto.computedValue"
    },
    {
      "key": "primaryColumns.sumabrutto.computedValue"
    },
    {
      "key": "primaryColumns.sugerowanyzadatek.computedValue"
    },
    {
      "key": "primaryColumns.sumarabatu.computedValue"
    },
    {
      "key": "primaryColumns.customColumn2.menuColor"
    },
    {
      "key": "primaryColumns.tabelanbpkurs.computedValue"
    },
    {
      "key": "primaryColumns.kurswgtabeli.computedValue"
    },
    {
      "key": "primaryColumns.narzut.computedValue"
    }
  ],
  "dynamicPropertyPathList": [
    {
      "key": "primaryColumns.customColumn1.borderRadius"
    }
  ],
  "dynamicTriggerPathList": [
    {
      "key": "onPageChange"
    },
    {
      "key": "onSearchTextChanged"
    },
    {
      "key": "onSort"
    },
    {
      "key": "primaryColumns.customColumn2.onClick"
    },
    {
      "key": "primaryColumns.customColumn4.onClick"
    },
    {
      "key": "onPageSizeChange"
    }
  ],
  "enableClientSideSearch": true,
  "enableServerSideFiltering": false,
  "hideCard": false,
  "horizontalAlignment": "LEFT",
  "iconSVG": "/static/media/icon.db8a9cbd.svg",
  "isLoading": false,
  "isSortable": true,
  "isVisible": "true",
  "isVisibleDownload": true,
  "isVisibleFilters": true,
  "isVisiblePagination": true,
  "isVisibleSearch": true,
  "key": "zba5qel0au",
  "label": "Data",
  "labelTextSize": "0.875rem",
  "leftColumn": 0,
  "onPageChange": "{{SelectQuery.run()}}",
  "onPageSizeChange": "{{SelectQuery.run()}}",
  "onSearchTextChanged": "{{SelectQuery.run()}}",
  "onSort": "{{SelectQuery.run()}}",
  "originalBottomRow": 89,
  "originalTopRow": 8,
  "parentColumnSpace": 16.3125,
  "parentId": "59rw5mx0bq",
  "parentRowSpace": 10,
  "primaryColumnId": "id_oferta",
  "primaryColumns": {
    "customColumn1": {
      "alias": "Lp.",
      "allowCellWrapping": false,
      "allowSameOptionsInNewRow": true,
      "buttonStyle": "rgb(3, 179, 101)",
      "columnType": "text",
      "computedValue": "{{data_table.processedTableData.map((currentRow, currentIndex) => ( currentIndex+1))}}",
      "currencyCode": "USD",
      "decimals": 0,
      "enableFilter": true,
      "enableSort": true,
      "horizontalAlignment": "LEFT",
      "id": "customColumn1",
      "index": 9,
      "isCellEditable": false,
      "isCellVisible": true,
      "isDerived": true,
      "isDisabled": false,
      "isDiscardVisible": true,
      "isEditable": false,
      "isSaveVisible": true,
      "isVisible": true,
      "label": "Lp.",
      "labelColor": "#FFFFFF",
      "notation": "standard",
      "originalId": "customColumn1",
      "sticky": "",
      "textSize": "0.875rem",
      "thousandSeparator": true,
      "validation": {},
      "verticalAlignment": "CENTER",
      "width": 150
    },
    "customColumn2": {
      "alias": "Usuń",
      "allowCellWrapping": false,
      "allowSameOptionsInNewRow": true,
      "buttonLabel": "USUŃ",
      "buttonStyle": "rgb(3, 179, 101)",
      "buttonVariant": "SECONDARY",
      "columnType": "iconButton",
      "computedValue": "",
      "currencyCode": "USD",
      "customAlias": "",
      "decimals": 0,
      "enableFilter": true,
      "enableSort": true,
      "horizontalAlignment": "LEFT",
      "iconName": "delete",
      "id": "customColumn2",
      "index": 10,
      "isCellEditable": false,
      "isCellVisible": true,
      "isDerived": true,
      "isDisabled": false,
      "isDiscardVisible": true,
      "isEditable": false,
      "isSaveVisible": true,
      "isVisible": true,
      "label": "Usuń",
      "labelColor": "#FFFFFF",
      "menuColor": "{{data_table.processedTableData.map((currentRow, currentIndex) => ( (appsmith.theme.colors.primaryColor)))}}",
      "menuItemsSource": "STATIC",
      "notation": "standard",
      "onClick": "{{showModal(Delete_Modal.name);}}",
      "originalId": "customColumn2",
      "sticky": "left",
      "textSize": "0.875rem",
      "thousandSeparator": true,
      "validation": {},
      "verticalAlignment": "CENTER",
      "width": 150
    },
    "customColumn4": {
      "alias": "DODAJ",
      "allowCellWrapping": false,
      "allowSameOptionsInNewRow": true,
      "borderRadius": "0.375rem",
      "boxShadow": "{{data_table.processedTableData.map((currentRow, currentIndex) => ( \"none\"))}}",
      "buttonColor": "#be185d",
      "buttonLabel": "DODAJ / ZOBACZ ",
      "buttonStyle": "rgb(3, 179, 101)",
      "columnType": "button",
      "computedValue": "",
      "currencyCode": "USD",
      "customAlias": "",
      "decimals": 0,
      "enableFilter": true,
      "enableSort": true,
      "horizontalAlignment": "LEFT",
      "id": "customColumn4",
      "index": 10,
      "isCellEditable": false,
      "isCellVisible": true,
      "isDerived": true,
      "isDisabled": false,
      "isDiscardVisible": true,
      "isEditable": false,
      "isSaveVisible": true,
      "isVisible": true,
      "label": "DODAJ",
      "labelColor": "#FFFFFF",
      "notation": "standard",
      "onClick": "{{storeValue('id_oferta', data_table.triggeredRow.id_oferta).then(() => {\n  storeValue('klient', data_table.triggeredRow.klient);\n  storeValue('numer', data_table.triggeredRow.numeroferty);\n  storeValue('id_klienta', Input2.text);\n  storeValue('data', data_table.triggeredRow.dataoferty);\n  navigateTo('Podsumowanie', {\n    id_oferta: appsmith.store.id_oferta,\n    klient: appsmith.store.klient,\n    data: appsmith.store.data,\n    numer: appsmith.store.numer,\n    id_klienta: appsmith.store.id_klienta\n  }, 'SAME_WINDOW');\n});}}",
      "originalId": "customColumn4",
      "sticky": "",
      "textSize": "0.875rem",
      "thousandSeparator": true,
      "validation": {},
      "verticalAlignment": "CENTER",
      "width": 150
    },
    "dataoferty": {
      "alias": "dataoferty",
      "allowCellWrapping": false,
      "allowSameOptionsInNewRow": true,
      "cellBackground": "",
      "columnType": "text",
      "computedValue": "{{data_table.processedTableData.map((currentRow, currentIndex) => ( currentRow.dataoferty))}}",
      "currencyCode": "USD",
      "decimals": 0,
      "enableFilter": true,
      "enableSort": true,
      "fontStyle": "",
      "horizontalAlignment": "LEFT",
      "id": "dataoferty",
      "index": 7,
      "inputFormat": "YYYY-MM-DD",
      "isCellEditable": false,
      "isCellVisible": true,
      "isDerived": false,
      "isDisabled": false,
      "isDiscardVisible": true,
      "isEditable": false,
      "isSaveVisible": true,
      "isVisible": true,
      "label": "Data",
      "notation": "standard",
      "originalId": "dataoferty",
      "outputFormat": "YYYY-MM-DD",
      "sticky": "",
      "textColor": "",
      "textSize": "0.875rem",
      "thousandSeparator": true,
      "validation": {},
      "verticalAlignment": "CENTER",
      "width": 150
    },
    "datawaznosci": {
      "alias": "datawaznosci",
      "allowCellWrapping": false,
      "allowSameOptionsInNewRow": true,
      "cellBackground": "",
      "columnType": "text",
      "computedValue": "{{data_table.processedTableData.map((currentRow, currentIndex) => ( currentRow[\"datawaznosci\"]))}}",
      "currencyCode": "USD",
      "decimals": 0,
      "enableFilter": true,
      "enableSort": true,
      "fontStyle": "",
      "horizontalAlignment": "LEFT",
      "id": "datawaznosci",
      "index": 15,
      "isCellEditable": false,
      "isCellVisible": true,
      "isDerived": false,
      "isDisabled": false,
      "isDiscardVisible": true,
      "isEditable": false,
      "isSaveVisible": true,
      "isVisible": false,
      "label": "datawaznosci",
      "notation": "standard",
      "originalId": "datawaznosci",
      "sticky": "",
      "textColor": "",
      "textSize": "0.875rem",
      "thousandSeparator": true,
      "validation": {},
      "verticalAlignment": "CENTER",
      "width": 150
    },
    "fk_klienci_oferty_id": {
      "alias": "fk_klienci_oferty_id",
      "allowCellWrapping": false,
      "allowSameOptionsInNewRow": true,
      "cellBackground": "",
      "columnType": "text",
      "computedValue": "{{data_table.processedTableData.map((currentRow, currentIndex) => ( currentRow[\"fk_klienci_oferty_id\"]))}}",
      "currencyCode": "USD",
      "decimals": 0,
      "enableFilter": true,
      "enableSort": true,
      "fontStyle": "",
      "horizontalAlignment": "LEFT",
      "id": "fk_klienci_oferty_id",
      "index": 6,
      "isCellEditable": false,
      "isCellVisible": true,
      "isDerived": false,
      "isDisabled": false,
      "isDiscardVisible": true,
      "isEditable": false,
      "isSaveVisible": true,
      "isVisible": false,
      "label": "fk_klienci_oferty_id",
      "notation": "standard",
      "originalId": "fk_klienci_oferty_id",
      "sticky": "",
      "textColor": "",
      "textSize": "0.875rem",
      "thousandSeparator": true,
      "validation": {},
      "verticalAlignment": "CENTER",
      "width": 150
    },
    "id_klient": {
      "alias": "id_klient",
      "allowCellWrapping": false,
      "allowSameOptionsInNewRow": true,
      "cellBackground": "",
      "columnType": "text",
      "computedValue": "{{data_table.processedTableData.map((currentRow, currentIndex) => ( currentRow[\"id_klient\"]))}}",
      "currencyCode": "USD",
      "decimals": 0,
      "enableFilter": true,
      "enableSort": true,
      "fontStyle": "",
      "horizontalAlignment": "LEFT",
      "id": "id_klient",
      "index": 5,
      "isCellEditable": false,
      "isCellVisible": true,
      "isDerived": false,
      "isDisabled": false,
      "isDiscardVisible": true,
      "isEditable": false,
      "isSaveVisible": true,
      "isVisible": false,
      "label": "id_klient",
      "notation": "standard",
      "originalId": "id_klient",
      "sticky": "",
      "textColor": "",
      "textSize": "0.875rem",
      "thousandSeparator": true,
      "validation": {},
      "verticalAlignment": "CENTER",
      "width": 150
    },
    "id_oferta": {
      "alias": "id_oferta",
      "allowCellWrapping": false,
      "allowSameOptionsInNewRow": true,
      "cellBackground": "",
      "columnType": "number",
      "computedValue": "{{data_table.processedTableData.map((currentRow, currentIndex) => ( currentRow[\"id_oferta\"]))}}",
      "currencyCode": "USD",
      "decimals": 0,
      "enableFilter": true,
      "enableSort": true,
      "fontStyle": "",
      "horizontalAlignment": "LEFT",
      "id": "id_oferta",
      "index": 0,
      "isCellEditable": false,
      "isCellVisible": true,
      "isDerived": false,
      "isDisabled": false,
      "isDiscardVisible": true,
      "isEditable": false,
      "isSaveVisible": true,
      "isVisible": false,
      "label": "id_oferta",
      "notation": "standard",
      "originalId": "id_oferta",
      "sticky": "",
      "textColor": "",
      "textSize": "0.875rem",
      "thousandSeparator": true,
      "validation": {},
      "verticalAlignment": "CENTER",
      "width": 150
    },
    "kategoria": {
      "alias": "kategoria",
      "allowCellWrapping": false,
      "allowSameOptionsInNewRow": true,
      "cellBackground": "",
      "columnType": "text",
      "computedValue": "{{data_table.processedTableData.map((currentRow, currentIndex) => ( currentRow.kategoria.map( (obj) =>{ return  {'label': obj.nazwakategorii, 'value': obj.nazwakategorii } })))}}",
      "currencyCode": "USD",
      "decimals": 0,
      "enableFilter": true,
      "enableSort": true,
      "fontStyle": "",
      "horizontalAlignment": "LEFT",
      "id": "kategoria",
      "index": 3,
      "isCellEditable": false,
      "isCellVisible": true,
      "isDerived": false,
      "isDisabled": false,
      "isDiscardVisible": true,
      "isEditable": false,
      "isSaveVisible": true,
      "isVisible": false,
      "label": "Kategoria",
      "notation": "standard",
      "originalId": "kategoria",
      "sticky": "",
      "textColor": "",
      "textSize": "0.875rem",
      "thousandSeparator": true,
      "validation": {},
      "verticalAlignment": "CENTER",
      "width": 150
    },
    "klient": {
      "alias": "klient",
      "allowCellWrapping": false,
      "allowSameOptionsInNewRow": true,
      "cellBackground": "",
      "columnType": "text",
      "computedValue": "{{data_table.processedTableData.map((currentRow, currentIndex) => ( currentRow[\"klient\"]))}}",
      "currencyCode": "USD",
      "decimals": 0,
      "enableFilter": true,
      "enableSort": true,
      "fontStyle": "",
      "horizontalAlignment": "LEFT",
      "id": "klient",
      "index": 1,
      "isCellEditable": false,
      "isCellVisible": true,
      "isDerived": false,
      "isDisabled": false,
      "isDiscardVisible": true,
      "isEditable": false,
      "isSaveVisible": true,
      "isVisible": true,
      "label": "Klient",
      "notation": "standard",
      "originalId": "klient",
      "sticky": "",
      "textColor": "",
      "textSize": "0.875rem",
      "thousandSeparator": true,
      "validation": {},
      "verticalAlignment": "CENTER",
      "width": 150
    },
    "komentarz": {
      "alias": "komentarz",
      "allowCellWrapping": false,
      "allowSameOptionsInNewRow": true,
      "cellBackground": "",
      "columnType": "text",
      "computedValue": "{{data_table.processedTableData.map((currentRow, currentIndex) => ( currentRow[\"komentarz\"]))}}",
      "currencyCode": "USD",
      "decimals": 0,
      "enableFilter": true,
      "enableSort": true,
      "fontStyle": "",
      "horizontalAlignment": "LEFT",
      "id": "komentarz",
      "index": 12,
      "isCellEditable": false,
      "isCellVisible": true,
      "isDerived": false,
      "isDisabled": false,
      "isDiscardVisible": true,
      "isEditable": false,
      "isSaveVisible": true,
      "isVisible": false,
      "label": "komentarz",
      "notation": "standard",
      "originalId": "komentarz",
      "sticky": "",
      "textColor": "",
      "textSize": "0.875rem",
      "thousandSeparator": true,
      "validation": {},
      "verticalAlignment": "CENTER",
      "width": 150
    },
    "kurseuro": {
      "alias": "kurseuro",
      "allowCellWrapping": false,
      "allowSameOptionsInNewRow": true,
      "cellBackground": "",
      "columnType": "text",
      "computedValue": "{{data_table.processedTableData.map((currentRow, currentIndex) => ( currentRow[\"kurseuro\"]))}}",
      "currencyCode": "USD",
      "decimals": 0,
      "enableFilter": true,
      "enableSort": true,
      "fontStyle": "",
      "horizontalAlignment": "LEFT",
      "id": "kurseuro",
      "index": 8,
      "isCellEditable": false,
      "isCellVisible": true,
      "isDerived": false,
      "isDisabled": false,
      "isDiscardVisible": true,
      "isEditable": false,
      "isSaveVisible": true,
      "isVisible": false,
      "label": "kurseuro",
      "notation": "standard",
      "originalId": "kurseuro",
      "sticky": "",
      "textColor": "",
      "textSize": "0.875rem",
      "thousandSeparator": true,
      "validation": {},
      "verticalAlignment": "CENTER",
      "width": 150
    },
    "kurswgtabeli": {
      "alias": "kurswgtabeli",
      "allowCellWrapping": false,
      "allowSameOptionsInNewRow": true,
      "cellBackground": "",
      "columnType": "number",
      "computedValue": "{{data_table.processedTableData.map((currentRow, currentIndex) => ( currentRow[\"kurswgtabeli\"]))}}",
      "currencyCode": "USD",
      "decimals": 0,
      "enableFilter": true,
      "enableSort": true,
      "fontStyle": "",
      "horizontalAlignment": "LEFT",
      "id": "kurswgtabeli",
      "index": 22,
      "isCellEditable": false,
      "isCellVisible": true,
      "isDerived": false,
      "isDisabled": false,
      "isDiscardVisible": true,
      "isEditable": false,
      "isSaveVisible": true,
      "isVisible": false,
      "label": "kurswgtabeli",
      "notation": "standard",
      "originalId": "kurswgtabeli",
      "sticky": "",
      "textColor": "",
      "textSize": "0.875rem",
      "thousandSeparator": true,
      "validation": {},
      "verticalAlignment": "CENTER",
      "width": 150
    },
    "narzut": {
      "alias": "narzut",
      "allowCellWrapping": false,
      "allowSameOptionsInNewRow": true,
      "cellBackground": "",
      "columnType": "number",
      "computedValue": "{{data_table.processedTableData.map((currentRow, currentIndex) => ( currentRow[\"narzut\"]))}}",
      "currencyCode": "USD",
      "decimals": 0,
      "enableFilter": true,
      "enableSort": true,
      "fontStyle": "",
      "horizontalAlignment": "LEFT",
      "id": "narzut",
      "index": 23,
      "isCellEditable": false,
      "isCellVisible": true,
      "isDerived": false,
      "isDisabled": false,
      "isDiscardVisible": true,
      "isEditable": false,
      "isSaveVisible": true,
      "isVisible": true,
      "label": "narzut",
      "notation": "standard",
      "originalId": "narzut",
      "sticky": "",
      "textColor": "",
      "textSize": "0.875rem",
      "thousandSeparator": true,
      "validation": {},
      "verticalAlignment": "CENTER",
      "width": 150
    },
    "numeroferty": {
      "alias": "numeroferty",
      "allowCellWrapping": false,
      "allowSameOptionsInNewRow": true,
      "cellBackground": "",
      "columnType": "number",
      "computedValue": "{{data_table.processedTableData.map((currentRow, currentIndex) => ( currentRow.numeroferty))}}",
      "currencyCode": "USD",
      "decimals": 0,
      "enableFilter": true,
      "enableSort": true,
      "fontStyle": "",
      "horizontalAlignment": "LEFT",
      "id": "numeroferty",
      "index": 2,
      "isCellEditable": false,
      "isCellVisible": true,
      "isDerived": false,
      "isDisabled": false,
      "isDiscardVisible": true,
      "isEditable": false,
      "isSaveVisible": true,
      "isVisible": true,
      "label": "Numer",
      "notation": "standard",
      "originalId": "numeroferty",
      "sticky": "",
      "textColor": "",
      "textSize": "0.875rem",
      "thousandSeparator": true,
      "validation": {},
      "verticalAlignment": "CENTER",
      "width": 150
    },
    "rabat": {
      "alias": "rabat",
      "allowCellWrapping": false,
      "allowSameOptionsInNewRow": true,
      "cellBackground": "",
      "columnType": "text",
      "computedValue": "{{data_table.processedTableData.map((currentRow, currentIndex) => ( currentRow[\"rabat\"]))}}",
      "currencyCode": "USD",
      "decimals": 0,
      "enableFilter": true,
      "enableSort": true,
      "fontStyle": "",
      "horizontalAlignment": "LEFT",
      "id": "rabat",
      "index": 11,
      "isCellEditable": false,
      "isCellVisible": true,
      "isDerived": false,
      "isDisabled": false,
      "isDiscardVisible": true,
      "isEditable": false,
      "isSaveVisible": true,
      "isVisible": false,
      "label": "rabat",
      "notation": "standard",
      "originalId": "rabat",
      "sticky": "",
      "textColor": "",
      "textSize": "0.875rem",
      "thousandSeparator": true,
      "validation": {},
      "verticalAlignment": "CENTER",
      "width": 150
    },
    "sugerowanyzadatek": {
      "alias": "sugerowanyzadatek",
      "allowCellWrapping": false,
      "allowSameOptionsInNewRow": true,
      "cellBackground": "",
      "columnType": "text",
      "computedValue": "{{data_table.processedTableData.map((currentRow, currentIndex) => ( currentRow[\"sugerowanyzadatek\"]))}}",
      "currencyCode": "USD",
      "decimals": 0,
      "enableFilter": true,
      "enableSort": true,
      "fontStyle": "",
      "horizontalAlignment": "LEFT",
      "id": "sugerowanyzadatek",
      "index": 19,
      "isCellEditable": false,
      "isCellVisible": true,
      "isDerived": false,
      "isDisabled": false,
      "isDiscardVisible": true,
      "isEditable": false,
      "isSaveVisible": true,
      "isVisible": false,
      "label": "sugerowanyzadatek",
      "notation": "standard",
      "originalId": "sugerowanyzadatek",
      "sticky": "",
      "textColor": "",
      "textSize": "0.875rem",
      "thousandSeparator": true,
      "validation": {},
      "verticalAlignment": "CENTER",
      "width": 150
    },
    "sumabrutto": {
      "alias": "sumabrutto",
      "allowCellWrapping": false,
      "allowSameOptionsInNewRow": true,
      "cellBackground": "",
      "columnType": "text",
      "computedValue": "{{data_table.processedTableData.map((currentRow, currentIndex) => ( currentRow[\"sumabrutto\"]))}}",
      "currencyCode": "USD",
      "decimals": 0,
      "enableFilter": true,
      "enableSort": true,
      "fontStyle": "",
      "horizontalAlignment": "LEFT",
      "id": "sumabrutto",
      "index": 18,
      "isCellEditable": false,
      "isCellVisible": true,
      "isDerived": false,
      "isDisabled": false,
      "isDiscardVisible": true,
      "isEditable": false,
      "isSaveVisible": true,
      "isVisible": false,
      "label": "sumabrutto",
      "notation": "standard",
      "originalId": "sumabrutto",
      "sticky": "",
      "textColor": "",
      "textSize": "0.875rem",
      "thousandSeparator": true,
      "validation": {},
      "verticalAlignment": "CENTER",
      "width": 150
    },
    "sumanetto": {
      "alias": "sumanetto",
      "allowCellWrapping": false,
      "allowSameOptionsInNewRow": true,
      "cellBackground": "",
      "columnType": "text",
      "computedValue": "{{data_table.processedTableData.map((currentRow, currentIndex) => ( currentRow[\"sumanetto\"]))}}",
      "currencyCode": "USD",
      "decimals": 0,
      "enableFilter": true,
      "enableSort": true,
      "fontStyle": "",
      "horizontalAlignment": "LEFT",
      "id": "sumanetto",
      "index": 17,
      "isCellEditable": false,
      "isCellVisible": true,
      "isDerived": false,
      "isDisabled": false,
      "isDiscardVisible": true,
      "isEditable": false,
      "isSaveVisible": true,
      "isVisible": false,
      "label": "sumanetto",
      "notation": "standard",
      "originalId": "sumanetto",
      "sticky": "",
      "textColor": "",
      "textSize": "0.875rem",
      "thousandSeparator": true,
      "validation": {},
      "verticalAlignment": "CENTER",
      "width": 150
    },
    "sumarabatu": {
      "alias": "sumarabatu",
      "allowCellWrapping": false,
      "allowSameOptionsInNewRow": true,
      "cellBackground": "",
      "columnType": "number",
      "computedValue": "{{data_table.processedTableData.map((currentRow, currentIndex) => ( currentRow[\"sumarabatu\"]))}}",
      "currencyCode": "USD",
      "decimals": 0,
      "enableFilter": true,
      "enableSort": true,
      "fontStyle": "",
      "horizontalAlignment": "LEFT",
      "id": "sumarabatu",
      "index": 20,
      "isCellEditable": false,
      "isCellVisible": true,
      "isDerived": false,
      "isDisabled": false,
      "isDiscardVisible": true,
      "isEditable": false,
      "isSaveVisible": true,
      "isVisible": false,
      "label": "sumarabatu",
      "notation": "standard",
      "originalId": "sumarabatu",
      "sticky": "",
      "textColor": "",
      "textSize": "0.875rem",
      "thousandSeparator": true,
      "validation": {},
      "verticalAlignment": "CENTER",
      "width": 150
    },
    "tabelanbpkurs": {
      "alias": "tabelanbpkurs",
      "allowCellWrapping": false,
      "allowSameOptionsInNewRow": true,
      "cellBackground": "",
      "columnType": "text",
      "computedValue": "{{data_table.processedTableData.map((currentRow, currentIndex) => ( currentRow[\"tabelanbpkurs\"]))}}",
      "currencyCode": "USD",
      "decimals": 0,
      "enableFilter": true,
      "enableSort": true,
      "fontStyle": "",
      "horizontalAlignment": "LEFT",
      "id": "tabelanbpkurs",
      "index": 21,
      "isCellEditable": false,
      "isCellVisible": true,
      "isDerived": false,
      "isDisabled": false,
      "isDiscardVisible": true,
      "isEditable": false,
      "isSaveVisible": true,
      "isVisible": false,
      "label": "tabelanbpkurs",
      "notation": "standard",
      "originalId": "tabelanbpkurs",
      "sticky": "",
      "textColor": "",
      "textSize": "0.875rem",
      "thousandSeparator": true,
      "validation": {},
      "verticalAlignment": "CENTER",
      "width": 150
    },
    "temat": {
      "alias": "temat",
      "allowCellWrapping": false,
      "allowSameOptionsInNewRow": true,
      "cellBackground": "",
      "columnType": "text",
      "computedValue": "{{data_table.processedTableData.map((currentRow, currentIndex) => ( currentRow[\"temat\"]))}}",
      "currencyCode": "USD",
      "decimals": 0,
      "enableFilter": true,
      "enableSort": true,
      "fontStyle": "",
      "horizontalAlignment": "LEFT",
      "id": "temat",
      "index": 8,
      "isCellEditable": false,
      "isCellVisible": true,
      "isDerived": false,
      "isDisabled": false,
      "isDiscardVisible": true,
      "isEditable": false,
      "isSaveVisible": true,
      "isVisible": true,
      "label": "Temat",
      "notation": "standard",
      "originalId": "temat",
      "sticky": "",
      "textColor": "",
      "textSize": "0.875rem",
      "thousandSeparator": true,
      "validation": {},
      "verticalAlignment": "CENTER",
      "width": 150
    },
    "vat": {
      "alias": "vat",
      "allowCellWrapping": false,
      "allowSameOptionsInNewRow": true,
      "cellBackground": "",
      "columnType": "text",
      "computedValue": "{{data_table.processedTableData.map((currentRow, currentIndex) => ( currentRow[\"vat\"]))}}",
      "currencyCode": "USD",
      "decimals": 0,
      "enableFilter": true,
      "enableSort": true,
      "fontStyle": "",
      "horizontalAlignment": "LEFT",
      "id": "vat",
      "index": 10,
      "isCellEditable": false,
      "isCellVisible": true,
      "isDerived": false,
      "isDisabled": false,
      "isDiscardVisible": true,
      "isEditable": false,
      "isSaveVisible": true,
      "isVisible": false,
      "label": "vat",
      "notation": "standard",
      "originalId": "vat",
      "sticky": "",
      "textColor": "",
      "textSize": "0.875rem",
      "thousandSeparator": true,
      "validation": {},
      "verticalAlignment": "CENTER",
      "width": 150
    },
    "waluta": {
      "alias": "waluta",
      "allowCellWrapping": false,
      "allowSameOptionsInNewRow": true,
      "cellBackground": "",
      "columnType": "text",
      "computedValue": "{{data_table.processedTableData.map((currentRow, currentIndex) => ( currentRow[\"waluta\"]))}}",
      "currencyCode": "USD",
      "decimals": 0,
      "enableFilter": true,
      "enableSort": true,
      "fontStyle": "",
      "horizontalAlignment": "LEFT",
      "id": "waluta",
      "index": 9,
      "isCellEditable": false,
      "isCellVisible": true,
      "isDerived": false,
      "isDisabled": false,
      "isDiscardVisible": true,
      "isEditable": false,
      "isSaveVisible": true,
      "isVisible": false,
      "label": "waluta",
      "notation": "standard",
      "originalId": "waluta",
      "sticky": "",
      "textColor": "",
      "textSize": "0.875rem",
      "thousandSeparator": true,
      "validation": {},
      "verticalAlignment": "CENTER",
      "width": 150
    },
    "warunkiplatnosci": {
      "alias": "warunkiplatnosci",
      "allowCellWrapping": false,
      "allowSameOptionsInNewRow": true,
      "cellBackground": "",
      "columnType": "text",
      "computedValue": "{{data_table.processedTableData.map((currentRow, currentIndex) => ( currentRow[\"warunkiplatnosci\"]))}}",
      "currencyCode": "USD",
      "decimals": 0,
      "enableFilter": true,
      "enableSort": true,
      "fontStyle": "",
      "horizontalAlignment": "LEFT",
      "id": "warunkiplatnosci",
      "index": 16,
      "isCellEditable": false,
      "isCellVisible": true,
      "isDerived": false,
      "isDisabled": false,
      "isDiscardVisible": true,
      "isEditable": false,
      "isSaveVisible": true,
      "isVisible": false,
      "label": "warunkiplatnosci",
      "notation": "standard",
      "originalId": "warunkiplatnosci",
      "sticky": "",
      "textColor": "",
      "textSize": "0.875rem",
      "thousandSeparator": true,
      "validation": {},
      "verticalAlignment": "CENTER",
      "width": 150
    },
    "wymaganyzadatek": {
      "alias": "wymaganyzadatek",
      "allowCellWrapping": false,
      "allowSameOptionsInNewRow": true,
      "cellBackground": "",
      "columnType": "text",
      "computedValue": "{{data_table.processedTableData.map((currentRow, currentIndex) => ( currentRow[\"wymaganyzadatek\"]))}}",
      "currencyCode": "USD",
      "decimals": 0,
      "enableFilter": true,
      "enableSort": true,
      "fontStyle": "",
      "horizontalAlignment": "LEFT",
      "id": "wymaganyzadatek",
      "index": 14,
      "isCellEditable": false,
      "isCellVisible": true,
      "isDerived": false,
      "isDisabled": false,
      "isDiscardVisible": true,
      "isEditable": false,
      "isSaveVisible": true,
      "isVisible": false,
      "label": "wymaganyzadatek",
      "notation": "standard",
      "originalId": "wymaganyzadatek",
      "sticky": "",
      "textColor": "",
      "textSize": "0.875rem",
      "thousandSeparator": true,
      "validation": {},
      "verticalAlignment": "CENTER",
      "width": 150
    },
    "wymaganyzadatekprocent": {
      "alias": "wymaganyzadatekprocent",
      "allowCellWrapping": false,
      "allowSameOptionsInNewRow": true,
      "cellBackground": "",
      "columnType": "text",
      "computedValue": "{{data_table.processedTableData.map((currentRow, currentIndex) => ( currentRow[\"wymaganyzadatekprocent\"]))}}",
      "currencyCode": "USD",
      "decimals": 0,
      "enableFilter": true,
      "enableSort": true,
      "fontStyle": "",
      "horizontalAlignment": "LEFT",
      "id": "wymaganyzadatekprocent",
      "index": 13,
      "isCellEditable": false,
      "isCellVisible": true,
      "isDerived": false,
      "isDisabled": false,
      "isDiscardVisible": true,
      "isEditable": false,
      "isSaveVisible": true,
      "isVisible": false,
      "label": "wymaganyzadatekprocent",
      "notation": "standard",
      "originalId": "wymaganyzadatekprocent",
      "sticky": "",
      "textColor": "",
      "textSize": "0.875rem",
      "thousandSeparator": true,
      "validation": {},
      "verticalAlignment": "CENTER",
      "width": 150
    }
  },
  "renderMode": "CANVAS",
  "rightColumn": 64,
  "searchKey": "",
  "serverSidePaginationEnabled": true,
  "tableData": "{{tabela_id_klient.data}}",
  "textSize": "0.875rem",
  "topRow": 10,
  "totalRecordsCount": "30",
  "type": "TABLE_WIDGET_V2",
  "variant": "VARIANT3",
  "version": 3,
  "verticalAlignment": "CENTER",
  "widgetId": "uji69u6swx",
  "widgetName": "data_table"
}